ana_cli/__init__.py
ana_cli/main.py
ana_cli-0.1.0.dist-info/entry_points.txt
ana_cli-0.1.0.dist-info/WHEEL
ana_cli-0.1.0.dist-info/METADATA
ana_cli-0.1.0.dist-info/RECORD
