Metadata-Version: 2.1
Name: ana-cli
Version: 0.1.0
Summary: 
Author: Matheus
Author-email: matheus.encode@gmail.com
Requires-Python: >=3.10,<4.0
Classifier: Programming Language :: Python :: 3
Classifier: Programming Language :: Python :: 3.10
Requires-Dist: typer[all] (>=0.6.1,<0.7.0)
